{
  "content": [
    {
      "emoji": "💡",
      "fallbackImageUrl": "https://telegram.org/img/emoji/40/F09F92A1.png",
      "type": "emojiImage"
    },
    {
      "data": "Cameco разбор",
      "type": "boldText"
    },
    {
      "data": " - пробуем новый формат постов!",
      "type": "regularText"
    },
    {
      "type": "lineBreak"
    },
    {
      "data": "Вы просили и мы сделали! Сегодня список разборов горнодобывающих компаний пополнит один из главных производителей урана – Cameco. С 2007 рынок радиоактивного металла находится в глубокой рецессии и наконец осенью 2021 котировки показали рост более чем на 60%. Оценим активы добытчика и его позиции в отрасли, детально проанализируем рынок на наличие драйверов роста, выясним причины резкого роста цены урана, определим, чем ядерная энергетика лучше ВИЭ и как тренд на экологическую ответственность повлияет на адресные рынки эмитента.",
      "type": "regularText"
    },
    {
      "type": "lineBreak"
    },
    {
      "emoji": "🔎",
      "fallbackImageUrl": "https://telegram.org/img/emoji/40/F09F948E.png",
      "type": "emojiImage"
    },
    {
      "data": " Читайте разбор по ссылке",
      "type": "boldText"
    }
  ],
  "date": "2021-09-24T11:46:01+00:00"
}