{
  "content": [
    {
      "emoji": "📌",
      "fallbackImageUrl": "https://telegram.org/img/emoji/40/F09F938C.png",
      "type": "emojiImage"
    },
    {
      "data": "Costco разбор #COST",
      "type": "boldText"
    },
    {
      "type": "lineBreak"
    },
    {
      "emoji": "💡",
      "fallbackImageUrl": "https://telegram.org/img/emoji/40/F09F92A1.png",
      "type": "emojiImage"
    },
    {
      "data": " Отрасль Discount stores – классически является одной из самых медленнорастущих и одновременно самой надежной. Даже в условиях тяжелейших кризисов уровень спроса сохраняется. Costco один из самых динамично развивающихся представителей, который делает ставку на нестандартную бизнес модель - прибыль более чем на половину формируется не из продаж. С другой стороны, эмитент оценен весьма дорого, стоит ли покупать Costco при текущей конъюнктуре рынка. ",
      "type": "regularText"
    },
    {
      "type": "lineBreak"
    },
    {
      "emoji": "🔎",
      "fallbackImageUrl": "https://telegram.org/img/emoji/40/F09F948E.png",
      "type": "emojiImage"
    },
    {
      "data": "Продолжение по ссылке",
      "type": "boldText"
    }
  ],
  "date": "2022-03-01T08:15:00+00:00"
}