{
  "content": [
    {
      "emoji": "💡",
      "fallbackImageUrl": "https://telegram.org/img/emoji/40/F09F92A1.png",
      "type": "emojiImage"
    },
    {
      "data": " МТС – все еще торгуется с дисконтом ",
      "type": "boldText"
    },
    {
      "type": "lineBreak"
    },
    {
      "data": "Отрасль: телекомы. Ведущая российская компания, предоставляющая пользователям цифровые, медийные и телекоммуникационные услуги. ",
      "type": "regularText"
    },
    {
      "type": "lineBreak"
    },
    {
      "data": "#MTSS",
      "type": "boldText"
    },
    {
      "type": "lineBreak"
    },
    {
      "data": "Отчетность за Q2’22 ",
      "type": "boldText"
    },
    {
      "emoji": "📋",
      "fallbackImageUrl": "https://telegram.org/img/emoji/40/F09F938B.png",
      "type": "emojiImage"
    },
    {
      "type": "lineBreak"
    },
    {
      "emoji": "💰",
      "fallbackImageUrl": "https://telegram.org/img/emoji/40/F09F92B0.png",
      "type": "emojiImage"
    },
    {
      "data": "Выручка 127,8 b₽ (+0,7% г/г)",
      "type": "regularText"
    },
    {
      "type": "lineBreak"
    },
    {
      "emoji": "💰",
      "fallbackImageUrl": "https://telegram.org/img/emoji/40/F09F92B0.png",
      "type": "emojiImage"
    },
    {
      "data": "Чистая прибыль 10,9 b₽ (-36,6% г/г) ",
      "type": "regularText"
    },
    {
      "type": "lineBreak"
    },
    {
      "emoji": "💰",
      "fallbackImageUrl": "https://telegram.org/img/emoji/40/F09F92B0.png",
      "type": "emojiImage"
    },
    {
      "data": "EPS 6,4 ₽ (-36,6% г/г)",
      "type": "regularText"
    },
    {
      "type": "lineBreak"
    },
    {
      "emoji": "🔎",
      "fallbackImageUrl": "https://telegram.org/img/emoji/40/F09F948E.png",
      "type": "emojiImage"
    },
    {
      "data": "Продолжение по ссылке:",
      "type": "boldText"
    }
  ],
  "date": "2022-11-09T05:12:00+00:00"
}