{
  "content": [
    {
      "emoji": "💡",
      "fallbackImageUrl": "https://telegram.org/img/emoji/40/F09F92A1.png",
      "type": "emojiImage"
    },
    {
      "data": "Распадская – экспресс обзор интересной опции на российском рынке среди сырьевых компаний #RASP",
      "type": "boldText"
    },
    {
      "type": "lineBreak"
    },
    {
      "data": "ПАО «Распадская» представляет собой группу интегрированных предприятий, специализирующуюся на производстве и реализации коксующегося угля и занимающую лидирующие позиции на российском рынке в своей отрасли. «Распадская» включает в себя несколько шахт, три обогатительных фабрики, предприятия производственной и транспортной инфраструктуры. Компания на 90,9% принадлежит металлургическому холдингу ЕВРАЗ. Распадская добывает коксующийся уголь, а ЕВРАЗ использует его в доменных печах для выплавки стальной продукции. ",
      "type": "regularText"
    },
    {
      "type": "lineBreak"
    },
    {
      "data": "Отчетность за FY21 ",
      "type": "boldText"
    },
    {
      "type": "lineBreak"
    },
    {
      "emoji": "💰",
      "fallbackImageUrl": "https://telegram.org/img/emoji/40/F09F92B0.png",
      "type": "emojiImage"
    },
    {
      "data": " Выручка 153,79 млрд ₽ (+244% г/г)",
      "type": "regularText"
    },
    {
      "type": "lineBreak"
    },
    {
      "emoji": "💰",
      "fallbackImageUrl": "https://telegram.org/img/emoji/40/F09F92B0.png",
      "type": "emojiImage"
    },
    {
      "data": " Чистая прибыль 63,87 млрд ₽ (+401% г/г)",
      "type": "regularText"
    },
    {
      "type": "lineBreak"
    },
    {
      "emoji": "💰",
      "fallbackImageUrl": "https://telegram.org/img/emoji/40/F09F92B0.png",
      "type": "emojiImage"
    },
    {
      "data": " EPS 95,35 (+412% г/г)",
      "type": "regularText"
    },
    {
      "type": "lineBreak"
    },
    {
      "data": "Выручка по сегментам:",
      "type": "boldText"
    },
    {
      "type": "lineBreak"
    },
    {
      "emoji": "📍",
      "fallbackImageUrl": "https://telegram.org/img/emoji/40/F09F938D.png",
      "type": "emojiImage"
    },
    {
      "data": " Реализация продукции 153,4 млрд ₽ (+267% г/г, 99,7% от выручки)",
      "type": "regularText"
    },
    {
      "type": "lineBreak"
    },
    {
      "emoji": "📍",
      "fallbackImageUrl": "https://telegram.org/img/emoji/40/F09F938D.png",
      "type": "emojiImage"
    },
    {
      "data": " Оказание услуг 426 млн ₽ (-85% г/г, 0,3% от выручки)",
      "type": "regularText"
    },
    {
      "type": "lineBreak"
    },
    {
      "emoji": "🔎",
      "fallbackImageUrl": "https://telegram.org/img/emoji/40/F09F948E.png",
      "type": "emojiImage"
    },
    {
      "data": "Продолжение по ссылке",
      "type": "boldText"
    }
  ],
  "date": "2022-04-01T05:15:00+00:00"
}